mathkit_vg/__init__.py
mathkit_vg/core.py
mathkit_vg-0.1.0.dist-info/licenses/LICENSE
mathkit_vg-0.1.0.dist-info/METADATA
mathkit_vg-0.1.0.dist-info/WHEEL
mathkit_vg-0.1.0.dist-info/top_level.txt
mathkit_vg-0.1.0.dist-info/RECORD
